spirits/__init__.py
spirits/__main__.py
spirits/command.py
spirits/example.py
spirits/gather.py
spirits/scatter.py
spirits/utils.py
spirits-1.0.0.dist-info/LICENSE
spirits-1.0.0.dist-info/METADATA
spirits-1.0.0.dist-info/WHEEL
spirits-1.0.0.dist-info/entry_points.txt
spirits-1.0.0.dist-info/RECORD
