Metadata-Version: 2.1
Name: spirits
Version: 1.0.0
Summary: spirits maker and gather via CLI or script
Home-page: https://github.com/HUGHNew/spirits
License: MIT
Author: Hugh Liu
Author-email: hugh.lpd@gmail.com
Requires-Python: >=3.6,<4.0
Classifier: License :: OSI Approved :: MIT License
Classifier: Programming Language :: Python :: 3
Classifier: Programming Language :: Python :: 3.6
Classifier: Programming Language :: Python :: 3.7
Classifier: Programming Language :: Python :: 3.8
Classifier: Programming Language :: Python :: 3.9
Classifier: Programming Language :: Python :: 3.10
Classifier: Programming Language :: Python :: 3.11
Classifier: Programming Language :: Python :: 3 :: Only
Classifier: Typing :: Typed
Requires-Dist: Pillow
Requires-Dist: requests
Requires-Dist: typer
Project-URL: Repository, https://github.com/HUGHNew/spirits
